flask_react/__init__.py
flask_react/cli.py
flask_react/exceptions.py
flask_react/extension.py
flask_react/node_renderer.py
flask_react_ssr-0.1.3.dist-info/licenses/LICENSE
flask_react_ssr-0.1.3.dist-info/METADATA
flask_react_ssr-0.1.3.dist-info/WHEEL
flask_react_ssr-0.1.3.dist-info/entry_points.txt
flask_react_ssr-0.1.3.dist-info/top_level.txt
flask_react_ssr-0.1.3.dist-info/RECORD
