Metadata-Version: 2.4
Name: flask-react-ssr
Version: 0.1.3
Summary: A Flask extension for server-side React component rendering using Node.js
Author-email: Baraa Khanfar <baraa60@icloud.com>
License-Expression: MIT
Project-URL: Homepage, https://github.com/baraakh30/flask-react
Project-URL: Repository, https://github.com/baraakh30/flask-react
Project-URL: Bug Tracker, https://github.com/baraakh30/flask-react/issues
Keywords: flask,react,ssr,server-side-rendering,node.js,jsx
Classifier: Development Status :: 3 - Alpha
Classifier: Intended Audience :: Developers
Classifier: Programming Language :: Python :: 3
Classifier: Programming Language :: Python :: 3.7
Classifier: Programming Language :: Python :: 3.8
Classifier: Programming Language :: Python :: 3.9
Classifier: Programming Language :: Python :: 3.10
Classifier: Programming Language :: Python :: 3.11
Classifier: Programming Language :: Python :: 3.12
Classifier: Framework :: Flask
Classifier: Topic :: Internet :: WWW/HTTP :: Dynamic Content
Classifier: Topic :: Software Development :: Libraries :: Python Modules
Requires-Python: >=3.7
License-File: LICENSE
Requires-Dist: Flask>=2.0.0
Requires-Dist: Jinja2>=3.0.0
Provides-Extra: dev
Requires-Dist: pytest>=6.0.0; extra == "dev"
Requires-Dist: pytest-cov>=2.10.0; extra == "dev"
Requires-Dist: black>=21.0.0; extra == "dev"
Requires-Dist: flake8>=4.0.0; extra == "dev"
Requires-Dist: mypy>=0.900; extra == "dev"
Requires-Dist: bump2version>=1.0.1; extra == "dev"
Dynamic: license-file
